{
  "appInfo" : {
    "build" : "211.7442.40",
    "buildDate" : "2021-06-01T03:17:35.284Z[UTC]",
    "productCode" : "IU",
    "generated" : "2021-06-08T07:59:47.755426Z",
    "os" : "macOS 10.16",
    "runtime" : "Oracle Corporation 11.0.9 11.0.9+7-LTS"
  },
  "runtimeInfo" : {
    "maxMemory" : 536870912,
    "numberOfProcessors" : 12,
    "maxNumberOfIndexingThreads" : 4,
    "maxSizeOfFileForIntelliSense" : 2560000,
    "maxSizeOfFileForContentLoading" : 20971520
  },
  "projectIndexingHistory" : {
    "projectName" : "LK-IDEAPlugins bak",
    "times" : {
      "totalUpdatingTime" : 1372006938,
      "indexingTime" : 40316000,
      "contentLoadingTime" : 4305043,
      "scanFilesTime" : 1130695000,
      "pushPropertiesTime" : 54635000,
      "indexExtensionsTime" : 0,
      "updatingStart" : "2021-06-08T07:59:46.380478Z",
      "updatingEnd" : "2021-06-08T07:59:47.752536Z",
      "totalSuspendedTime" : 0,
      "wasInterrupted" : false
    },
    "fileCount" : {
      "numberOfFileProviders" : 18,
      "numberOfScannedFiles" : 705,
      "numberOfFilesIndexedByInfrastructureExtensionsDuringScan" : 0,
      "numberOfFilesScheduledForIndexingAfterScan" : 7,
      "numberOfFilesIndexedByInfrastructureExtensionsDuringIndexingStage" : 7,
      "numberOfFilesIndexedWithLoadingContent" : 7
    },
    "totalStatsPerFileType" : [ {
      "fileType" : "JAVA",
      "partOfTotalProcessingTime" : {
        "part" : 55669367,
        "total" : 55669367
      },
      "partOfTotalContentLoadingTime" : {
        "part" : 11797925,
        "total" : 11797925
      },
      "totalNumberOfFiles" : 7,
      "totalFilesSize" : 19836,
      "indexingSpeed" : {
        "totalBytes" : 19836,
        "totalTime" : 55669367
      },
      "biggestContributors" : [ {
        "providerName" : "Module 'DJ-IDEAPlugins'",
        "numberOfFiles" : 7,
        "totalFilesSize" : 19836,
        "partOfTotalProcessingTimeOfThisFileType" : {
          "part" : 55669367,
          "total" : 55669367
        }
      } ]
    } ],
    "totalStatsPerIndexer" : [ ],
    "scanningStatistics" : [ {
      "providerName" : "com.intellij.javaee.ExternalResourcesRootsProvider@62b996fc",
      "numberOfScannedFiles" : 580,
      "numberOfSkippedFiles" : 11,
      "numberOfFilesForIndexing" : 0,
      "numberOfFilesFullyIndexedByInfrastructureExtensions" : 0,
      "scanningTime" : 442147725,
      "timeProcessingUpToDateFiles" : 25747348,
      "timeUpdatingContentLessIndexes" : 22240250,
      "timeIndexingWithoutContent" : 0
    }, {
      "providerName" : "Module 'DJ-IDEAPlugins'",
      "numberOfScannedFiles" : 27,
      "numberOfSkippedFiles" : 0,
      "numberOfFilesForIndexing" : 7,
      "numberOfFilesFullyIndexedByInfrastructureExtensions" : 0,
      "scanningTime" : 170097245,
      "timeProcessingUpToDateFiles" : 6246780,
      "timeUpdatingContentLessIndexes" : 865945,
      "timeIndexingWithoutContent" : 3479700
    }, {
      "providerName" : "com.intellij.lang.typescript.library.TypeScriptLibraryIndexableSetContributor@4d8efce6",
      "numberOfScannedFiles" : 38,
      "numberOfSkippedFiles" : 22,
      "numberOfFilesForIndexing" : 0,
      "numberOfFilesFullyIndexedByInfrastructureExtensions" : 0,
      "scanningTime" : 164117080,
      "timeProcessingUpToDateFiles" : 31709235,
      "timeUpdatingContentLessIndexes" : 1508075,
      "timeIndexingWithoutContent" : 0
    }, {
      "providerName" : "com.intellij.lang.javascript.index.JSIndexedRootProvider@27c36930",
      "numberOfScannedFiles" : 30,
      "numberOfSkippedFiles" : 42,
      "numberOfFilesForIndexing" : 0,
      "numberOfFilesFullyIndexedByInfrastructureExtensions" : 0,
      "scanningTime" : 154899122,
      "timeProcessingUpToDateFiles" : 20594095,
      "timeUpdatingContentLessIndexes" : 963765,
      "timeIndexingWithoutContent" : 0
    }, {
      "providerName" : "com.intellij.lang.javascript.index.JSIndexedRootProvider@27c36930",
      "numberOfScannedFiles" : 13,
      "numberOfSkippedFiles" : 0,
      "numberOfFilesForIndexing" : 0,
      "numberOfFilesFullyIndexedByInfrastructureExtensions" : 0,
      "scanningTime" : 124465061,
      "timeProcessingUpToDateFiles" : 18768918,
      "timeUpdatingContentLessIndexes" : 919709,
      "timeIndexingWithoutContent" : 0
    }, {
      "providerName" : "com.intellij.httpClient.http.request.HttpRequestCollectionProvider@218f5d06",
      "numberOfScannedFiles" : 7,
      "numberOfSkippedFiles" : 0,
      "numberOfFilesForIndexing" : 0,
      "numberOfFilesFullyIndexedByInfrastructureExtensions" : 0,
      "scanningTime" : 116642910,
      "timeProcessingUpToDateFiles" : 5635568,
      "timeUpdatingContentLessIndexes" : 253387,
      "timeIndexingWithoutContent" : 0
    }, {
      "providerName" : "org.jetbrains.plugins.scss.index.SassScssIndexedRootProvider@22815951",
      "numberOfScannedFiles" : 8,
      "numberOfSkippedFiles" : 0,
      "numberOfFilesForIndexing" : 0,
      "numberOfFilesFullyIndexedByInfrastructureExtensions" : 0,
      "scanningTime" : 114718003,
      "timeProcessingUpToDateFiles" : 8383386,
      "timeUpdatingContentLessIndexes" : 611710,
      "timeIndexingWithoutContent" : 0
    }, {
      "providerName" : "com.intellij.ide.scratch.ScratchesAndConsolesIndexSetContributor@37ddad1",
      "numberOfScannedFiles" : 1,
      "numberOfSkippedFiles" : 0,
      "numberOfFilesForIndexing" : 0,
      "numberOfFilesFullyIndexedByInfrastructureExtensions" : 0,
      "scanningTime" : 96564105,
      "timeProcessingUpToDateFiles" : 799147,
      "timeUpdatingContentLessIndexes" : 33930,
      "timeIndexingWithoutContent" : 0
    }, {
      "providerName" : "com.intellij.httpClient.http.request.run.HttpClientDynamicVariablesStubController@3e408cf3",
      "numberOfScannedFiles" : 1,
      "numberOfSkippedFiles" : 0,
      "numberOfFilesForIndexing" : 0,
      "numberOfFilesFullyIndexedByInfrastructureExtensions" : 0,
      "scanningTime" : 2746903,
      "timeProcessingUpToDateFiles" : 1093667,
      "timeUpdatingContentLessIndexes" : 23643,
      "timeIndexingWithoutContent" : 0
    }, {
      "providerName" : "com.intellij.javaee.ExternalResourcesRootsProvider@62b996fc",
      "numberOfScannedFiles" : 0,
      "numberOfSkippedFiles" : 0,
      "numberOfFilesForIndexing" : 0,
      "numberOfFilesFullyIndexedByInfrastructureExtensions" : 0,
      "scanningTime" : 0,
      "timeProcessingUpToDateFiles" : 0,
      "timeUpdatingContentLessIndexes" : 0,
      "timeIndexingWithoutContent" : 0
    }, {
      "providerName" : "com.intellij.ide.scratch.ScratchesAndConsolesIndexSetContributor@37ddad1",
      "numberOfScannedFiles" : 0,
      "numberOfSkippedFiles" : 0,
      "numberOfFilesForIndexing" : 0,
      "numberOfFilesFullyIndexedByInfrastructureExtensions" : 0,
      "scanningTime" : 0,
      "timeProcessingUpToDateFiles" : 0,
      "timeUpdatingContentLessIndexes" : 0,
      "timeIndexingWithoutContent" : 0
    }, {
      "providerName" : "org.jetbrains.plugins.scss.index.SassScssIndexedRootProvider@22815951",
      "numberOfScannedFiles" : 0,
      "numberOfSkippedFiles" : 0,
      "numberOfFilesForIndexing" : 0,
      "numberOfFilesFullyIndexedByInfrastructureExtensions" : 0,
      "scanningTime" : 0,
      "timeProcessingUpToDateFiles" : 0,
      "timeUpdatingContentLessIndexes" : 0,
      "timeIndexingWithoutContent" : 0
    }, {
      "providerName" : "com.intellij.lang.typescript.library.TypeScriptLibraryIndexableSetContributor@4d8efce6",
      "numberOfScannedFiles" : 0,
      "numberOfSkippedFiles" : 0,
      "numberOfFilesForIndexing" : 0,
      "numberOfFilesFullyIndexedByInfrastructureExtensions" : 0,
      "scanningTime" : 0,
      "timeProcessingUpToDateFiles" : 0,
      "timeUpdatingContentLessIndexes" : 0,
      "timeIndexingWithoutContent" : 0
    }, {
      "providerName" : "org.jetbrains.kotlin.idea.core.script.dependencies.KotlinScriptDependenciesIndexableSetContributor@12655f95",
      "numberOfScannedFiles" : 0,
      "numberOfSkippedFiles" : 0,
      "numberOfFilesForIndexing" : 0,
      "numberOfFilesFullyIndexedByInfrastructureExtensions" : 0,
      "scanningTime" : 0,
      "timeProcessingUpToDateFiles" : 0,
      "timeUpdatingContentLessIndexes" : 0,
      "timeIndexingWithoutContent" : 0
    }, {
      "providerName" : "com.intellij.httpClient.http.request.HttpRequestCollectionProvider@218f5d06",
      "numberOfScannedFiles" : 0,
      "numberOfSkippedFiles" : 0,
      "numberOfFilesForIndexing" : 0,
      "numberOfFilesFullyIndexedByInfrastructureExtensions" : 0,
      "scanningTime" : 0,
      "timeProcessingUpToDateFiles" : 0,
      "timeUpdatingContentLessIndexes" : 0,
      "timeIndexingWithoutContent" : 0
    }, {
      "providerName" : "org.jetbrains.kotlin.idea.core.script.dependencies.KotlinScriptDependenciesIndexableSetContributor@12655f95",
      "numberOfScannedFiles" : 0,
      "numberOfSkippedFiles" : 0,
      "numberOfFilesForIndexing" : 0,
      "numberOfFilesFullyIndexedByInfrastructureExtensions" : 0,
      "scanningTime" : 0,
      "timeProcessingUpToDateFiles" : 0,
      "timeUpdatingContentLessIndexes" : 0,
      "timeIndexingWithoutContent" : 0
    }, {
      "providerName" : "com.intellij.httpClient.http.request.run.HttpClientDynamicVariablesStubController@3e408cf3",
      "numberOfScannedFiles" : 0,
      "numberOfSkippedFiles" : 0,
      "numberOfFilesForIndexing" : 0,
      "numberOfFilesFullyIndexedByInfrastructureExtensions" : 0,
      "scanningTime" : 0,
      "timeProcessingUpToDateFiles" : 0,
      "timeUpdatingContentLessIndexes" : 0,
      "timeIndexingWithoutContent" : 0
    }, {
      "providerName" : "com.intellij.openapi.roots.ImmutableSyntheticLibrary@15168add",
      "numberOfScannedFiles" : 0,
      "numberOfSkippedFiles" : 0,
      "numberOfFilesForIndexing" : 0,
      "numberOfFilesFullyIndexedByInfrastructureExtensions" : 0,
      "scanningTime" : 0,
      "timeProcessingUpToDateFiles" : 0,
      "timeUpdatingContentLessIndexes" : 0,
      "timeIndexingWithoutContent" : 0
    } ],
    "fileProviderStatistics" : [ {
      "providerName" : "Module 'DJ-IDEAPlugins'",
      "totalNumberOfIndexedFiles" : 7,
      "totalNumberOfFilesFullyIndexedByExtensions" : 7,
      "totalIndexingTime" : 20313661,
      "contentLoadingTime" : 4305043,
      "numberOfTooLargeForIndexingFiles" : 0,
      "slowIndexedFiles" : [ ]
    } ]
  }
}